{
  "id": "bookings",
  "label": "Bookings",
  "description": "Service bookings with menus and embedded calendars.",
  "pages": {
    "index.html": {
      "sections": [
        "seo-base",
        "nav",
        "hero",
        "about",
        "services-list",
        "features-grid",
        "team",
        "testimonials",
        "pricing-table",
        "faq",
        "service-menu",
        "calendar-embed",
        "hours-location",
        "cta-banner",
        "contact",
        "footer"
      ]
    }
  },
  "features": {
    "formToEmail": true,
    "mapEmbed": true,
    "lightbox": false,
    "cart": false,
    "calendarEmbed": true,
    "blogEngine": false,
    "multiStepForm": false
  },
  "defaultTheme": {
    "primary": "#4338ca",
    "secondary": "#312e81",
    "accent": "#f59e0b",
    "bg": "#ffffff",
    "text": "#111827",
    "headingFont": "Inter",
    "bodyFont": "Inter"
  }
}
